Metadata-Version: 2.1
Name: glcd-jhd128x64
Version: 1.0.1
Summary: A simple library for controlling JHD128X64E GLCDs
Home-page: https://github.com/factana/glcd-jhd128x64e-ks0108
Author: Eldho K K
Author-email: eldho.kuriakose@factana.com
License: MIT
Keywords: library glcd display ks0108 interface raspberrypi factana
Platform: UNKNOWN
Classifier: License :: OSI Approved :: MIT License
Classifier: Operating System :: POSIX
Classifier: Operating System :: Unix
Classifier: Programming Language :: Python :: 3.10
Classifier: Topic :: System :: Hardware :: Hardware Drivers
Classifier: Topic :: Software Development :: Libraries :: Python Modules
License-File: LICENSE
